randomroller/__init__.py
randomroller/_version.py
randomroller/cli.py
randomroller/dice.py
randomroller/die.py
randomroller/truerng.py
randomroller-2.2.1.dist-info/METADATA
randomroller-2.2.1.dist-info/RECORD
randomroller-2.2.1.dist-info/WHEEL
randomroller-2.2.1.dist-info/entry_points.txt
randomroller-2.2.1.dist-info/top_level.txt
