Metadata-Version: 2.1
Name: randomroller
Version: 2.2.1
Summary: An extra random dice roller
Home-page: https://github.com/onlyhavecans/randomroller
Author: David Aronsohn
Author-email: squirrel@wearing.black
License: UNKNOWN
Platform: any
Requires: pyserial
Requires-Dist: pyserial
